bootstrap_vi
