Metadata-Version: 1.0
Name: bootstrap-vi
Version: 0.0.4
Summary: Bootstrap virtualenv without pip or easy_install
Home-page: https://github.com/necrolyte2/bootstrap_vi
Author: Tyghe Vallard
Author-email: vallardt@gmail.com
License: MIT
Keywords: bootstrap,virtualenv
Platform: UNKNOWN
